slice_finder/__init__.py
slice_finder/data_connectors/__init__.py
slice_finder/data_connectors/data_connector.py
slice_finder/data_connectors/pandas.py
slice_finder/data_structures/__init__.py
slice_finder/data_structures/data_structure.py
slice_finder/data_structures/flattened_lgbm.py
slice_finder/data_structures/lgbm.py
slice_finder/slice_finders/__init__.py
slice_finder/slice_finders/ga.py
slice_finder/slice_finders/ga_mu_plus_lambda.py
slice_finder/slice_finders/slice_finder.py
slice_finder/slice_finders/uniform.py
slice_finder/types.py
slice_finder-0.0.22.dist-info/WHEEL
slice_finder-0.0.22.dist-info/METADATA
slice_finder-0.0.22.dist-info/RECORD
