Metadata-Version: 2.1
Name: slice-finder
Version: 0.0.22
Summary: Slice Finder: A Framework for Slice Discovery
Home-page: https://github.com/igaloly/slice_finder
License: MIT
Keywords: slice discovery,slice detection,subgroup discovery,subgroup detection,slice finding
Author: Igal Leikin
Author-email: igaloly@gmail.com
Requires-Python: >=3.10,<4.0
Classifier: Intended Audience :: Science/Research
Classifier: License :: OSI Approved :: MIT License
Classifier: Programming Language :: Python :: 3
Classifier: Programming Language :: Python :: 3.10
Classifier: Programming Language :: Python :: 3.11
Classifier: Programming Language :: Python :: 3
Classifier: Topic :: Scientific/Engineering
Requires-Dist: deap (>=1.3,<2.0)
Requires-Dist: lightgbm (>=3.0.0,<4.0.0)
Requires-Dist: numpy (>=1.20.0,<2.0.0)
Requires-Dist: pandas (>=1.2.5,<2.0.0)
Project-URL: Repository, https://github.com/igaloly/slice_finder
